Metadata-Version: 2.1
Name: odoo13-addon-account-tax-balance
Version: 13.0.1.0.3
Summary: Compute tax balances based on date range
Home-page: https://github.com/OCA/account-financial-reporting
Author: Agile Business Group, Therp BV, Tecnativa, ACSONE SA/NV, Odoo Community Association (OCA)
Author-email: support@odoo-community.org
License: AGPL-3
Platform: UNKNOWN
Classifier: Programming Language :: Python
Classifier: Framework :: Odoo
Classifier: Framework :: Odoo :: 13.0
Classifier: License :: OSI Approved :: GNU Affero General Public License v3
Classifier: Development Status :: 6 - Mature
Requires-Python: >=3.5
Requires-Dist: odoo13-addon-date-range
Requires-Dist: odoo (<13.1dev,>=13.0a)
